odoo/addons/account_payment_view_check_number/README.rst
odoo/addons/account_payment_view_check_number/__init__.py
odoo/addons/account_payment_view_check_number/__manifest__.py
odoo/addons/account_payment_view_check_number/i18n/account_payment_view_check_number.pot
odoo/addons/account_payment_view_check_number/i18n/sl.po
odoo/addons/account_payment_view_check_number/readme/CONFIGURE.rst
odoo/addons/account_payment_view_check_number/readme/CONTRIBUTORS.rst
odoo/addons/account_payment_view_check_number/readme/DESCRIPTION.rst
odoo/addons/account_payment_view_check_number/readme/USAGE.rst
odoo/addons/account_payment_view_check_number/static/description/icon.png
odoo/addons/account_payment_view_check_number/static/description/index.html
odoo/addons/account_payment_view_check_number/views/account_payment_view.xml
odoo14_addon_account_payment_view_check_number-14.0.1.0.1.dev6.dist-info/METADATA
odoo14_addon_account_payment_view_check_number-14.0.1.0.1.dev6.dist-info/WHEEL
odoo14_addon_account_payment_view_check_number-14.0.1.0.1.dev6.dist-info/top_level.txt
odoo14_addon_account_payment_view_check_number-14.0.1.0.1.dev6.dist-info/RECORD
